{
  "error": "Command '['ssh', '-i', '/Users/edward/.ssh/diloco_lambda', '-o', 'StrictHostKeyChecking=no', '-o', 'UserKnownHostsFile=/dev/null', '-o', 'ConnectTimeout=10', 'ubuntu@129.213.19.183', 'cd /home/ubuntu/diloco_l5_src && env PYTHONPATH=src python3 -m decodilo.cli learner run --learner-id learner-0 --run-id lambda-largermodel-85k-hardened-20260701164443 --host 132.145.198.74 --port 28080 --workdir /home/ubuntu/lambda_l5_run --steps 8 --local-steps-per-sync 2 --heartbeat-interval-seconds 0.05 --step-delay-seconds 0.05 --learner-lr 0.05 --trainer-type torch_causal_lm --trainer-config-json \\'{\"optimizer\":\"adamw\",\"device\":\"cuda\",\"vocab_size\":128,\"seq_len\":32,\"batch_size\":2,\"d_model\":64,\"num_layers\":2,\"num_heads\":4,\"learning_rate\":0.001,\"mlp_ratio\":2.0}\\' --seed 123 --reconnect-timeout-seconds 120.0 --payload-storage-mode chunked --global-update-storage-mode chunked --inline-payload-max-bytes 1024 --chunk-size-bytes 1048576 --tensor-artifact-codec binary_v1 --fragment-artifact-codec binary_v1 --artifact-transfer-mode object_store --artifact-storage-backend auto > /home/ubuntu/lambda_l5_run/learner-0.stdout 2> /home/ubuntu/lambda_l5_run/learner-0.stderr']' timed out after 30 seconds"
}
